setup.cfg
setup.py
bin/cli-aoke
cli_aoke.egg-info/PKG-INFO
cli_aoke.egg-info/SOURCES.txt
cli_aoke.egg-info/dependency_links.txt
cli_aoke.egg-info/requires.txt
cli_aoke.egg-info/top_level.txt
src/__init__.py
src/lyrics.py
src/scrape.py
src/songs.py
src/threads.py