Metadata-Version: 1.1
Name: cli-aoke
Version: 1.1.0
Summary: Command Line Karaoke
Home-page: https://github.com/jfrazelle/cli-aoke
Author: Jessica Frazelle
Author-email: jfrazelle@me.com
License: MIT
Keywords: karaoke,command,line,magic
Platform: UNKNOWN
Classifier: Development Status :: 5 - Production/Stable
Classifier: Intended Audience :: Developers
Classifier: Programming Language :: Python
Classifier: Operating System :: OS Independent
Classifier: Topic :: Internet :: WWW/HTTP
Classifier: Topic :: Software Development :: Libraries :: Python Modules
